wdbse/__init__.py
wdbse/functions.py
wdbse/main.py
wdbse/test/__init__.py
wdbse/test/test_functions.py
wdbse-0.1.0.dist-info/LICENSE
wdbse-0.1.0.dist-info/METADATA
wdbse-0.1.0.dist-info/WHEEL
wdbse-0.1.0.dist-info/top_level.txt
wdbse-0.1.0.dist-info/RECORD
