Metadata-Version: 2.1
Name: wdbse
Version: 0.1.0
Author: PunchyArchy
Author-email: ksmdrmvscthny@gmail.com
License-File: LICENSE
Requires-Dist: wsqluse
